{"autoplayBgm":false,"autoplayBgs":false,"battleback1Name":"","battleback2Name":"","bgm":{"name":"","pan":0,"pitch":100,"volume":90},"bgs":{"name":"","pan":0,"pitch":100,"volume":90},"disableDashing":false,"displayName":"","encounterList":[],"encounterStep":30,"height":11,"note":"","parallaxLoopX":false,"parallaxLoopY":false,"parallaxName":"","parallaxShow":true,"parallaxSx":0,"parallaxSy":0,"scrollType":0,"specifyBattleback":false,"tilesetId":35,"width":9,"data":[6176,6176,6200,6623,6192,6176,6176,6176,6176,6176,6176,6200,4010,6192,6176,6176,6176,6176,6180,6204,6214,4000,6192,6176,6176,6176,6176,6200,6618,6622,4012,6192,6176,6176,6176,6176,6214,3722,2907,2909,6194,6204,6204,6204,6184,2909,3712,6211,6209,6215,6615,4010,6615,6192,6212,3712,6220,6618,6622,6621,4000,6617,6192,6200,3712,6623,4002,3988,3988,3971,4004,6192,6200,3724,4011,3997,3996,3996,3996,4006,6192,6206,6209,6209,6209,6209,6209,6209,6209,6205,6619,6618,6618,6618,6618,6618,6618,6618,6622,0,0,0,0,0,0,0,0,0,0,0,0,0,0,0,0,0,0,0,0,0,0,0,0,0,0,0,0,0,0,0,0,0,0,0,0,0,0,0,0,0,0,0,0,0,0,0,0,0,0,0,0,0,0,0,0,0,0,0,0,0,0,0,0,0,0,0,0,0,0,0,0,0,0,0,0,0,0,0,0,0,0,0,0,0,0,0,0,0,0,0,0,0,0,0,0,0,0,0,0,0,0,0,0,0,0,0,0,0,0,0,0,0,0,0,0,0,0,0,0,0,0,0,0,0,0,0,0,0,0,0,0,0,0,0,0,0,0,0,0,0,0,0,0,0,0,0,0,0,0,194,195,0,0,0,0,0,0,0,202,203,0,0,0,0,0,0,0,0,0,0,0,0,0,0,0,0,0,0,0,0,0,0,0,0,0,0,0,0,0,0,0,0,0,0,0,0,0,0,0,0,417,0,0,0,0,0,0,0,0,425,0,0,0,0,0,0,0,0,912,0,0,0,0,0,0,0,0,920,0,0,0,0,0,0,0,0,0,0,0,0,0,0,0,0,0,0,0,0,180,181,0,0,0,0,419,416,0,188,189,0,0,0,0,427,424,95,0,95,0,0,0,0,0,0,0,0,0,0,0,0,0,0,0,0,0,0,0,0,0,0,0,0,0,0,0,0,0,0,0,0,0,0,0,0,0,0,0,0,5,0,0,0,0,0,0,0,0,5,0,0,0,0,0,0,0,0,5,0,0,0,0,0,0,5,0,0,0,0,0,0,0,0,0,0,0,0,0,5,0,0,0,0,0,0,0,0,5,0,0,0,5,0,5,0,0,0,0,0,0,5,0,0,0,0,0,0,0,0,0,0,0,0,0,0,0,0,0,0,0,0,0,0,0,0,0,0,0,0,0,0,0,0,0,0,0,0,0,0,0,0,0,0,0,0,0,0,0,0,0,0,0,0,0,0,0,0,0,0,0,0,0,0,0,0,0,0,0,0,0,0,0,0,0,0,0,0,0,0,0,0,0,0,0,0,0,0,0,0,0,0,0,0,0,0,0,0,0,0,0,0,0,0,0,0,0,0,0,0,0,0,0,0,0,0,0,0,0,0,0,0,0,0,0,0],"events":[null,{"id":1,"name":"EV001","note":"","pages":[{"conditions":{"actorId":1,"actorValid":false,"itemId":1,"itemValid":false,"selfSwitchCh":"A","selfSwitchValid":false,"switch1Id":1,"switch1Valid":false,"switch2Id":1,"switch2Valid":false,"variableId":1,"variableValid":false,"variableValue":0},"directionFix":false,"image":{"characterIndex":0,"characterName":"","direction":2,"pattern":0,"tileId":0},"list":[{"code":201,"indent":0,"parameters":[0,57,12,10,4,0]},{"code":0,"indent":0,"parameters":[]}],"moveFrequency":3,"moveRoute":{"list":[{"code":0,"parameters":[]}],"repeat":true,"skippable":false,"wait":false},"moveSpeed":3,"moveType":0,"priorityType":0,"stepAnime":false,"through":false,"trigger":1,"walkAnime":true}],"x":0,"y":5},{"id":2,"name":"EV002","note":"","pages":[{"conditions":{"actorId":1,"actorValid":false,"itemId":1,"itemValid":false,"selfSwitchCh":"A","selfSwitchValid":false,"switch1Id":56,"switch1Valid":true,"switch2Id":1,"switch2Valid":false,"variableId":1,"variableValid":false,"variableValue":0},"directionFix":false,"image":{"tileId":0,"characterName":"!Flame","direction":2,"pattern":1,"characterIndex":6},"list":[{"code":205,"indent":0,"parameters":[-1,{"list":[{"code":19,"indent":null},{"code":0}],"repeat":false,"skippable":false,"wait":true}]},{"code":505,"indent":0,"parameters":[{"code":19,"indent":null}]},{"code":230,"indent":0,"parameters":[60]},{"code":213,"indent":0,"parameters":[-1,1,false]},{"code":230,"indent":0,"parameters":[60]},{"code":101,"indent":0,"parameters":["",0,0,2]},{"code":401,"indent":0,"parameters":["\\N<Naoto>(Huh...?)"]},{"code":230,"indent":0,"parameters":[60]},{"code":241,"indent":0,"parameters":[{"name":"kaede吐息 (1)","volume":90,"pitch":100,"pan":0}]},{"code":245,"indent":0,"parameters":[{"name":"くちゅ音１","volume":90,"pitch":100,"pan":0}]},{"code":231,"indent":0,"parameters":[1,"kaede onani1　kage",0,0,0,0,100,100,0,0]},{"code":232,"indent":0,"parameters":[1,0,0,0,0,0,100,100,255,0,60,true]},{"code":101,"indent":0,"parameters":["",0,0,2]},{"code":401,"indent":0,"parameters":["\\N<Kaede>Ahn... mhmm... ngh..."]},{"code":101,"indent":0,"parameters":["",0,0,2]},{"code":401,"indent":0,"parameters":["\\N<Naoto>(K-Kaede...?)"]},{"code":101,"indent":0,"parameters":["",0,0,2]},{"code":401,"indent":0,"parameters":["\\N<Kaede>Ngh... mhmm... ahh..."]},{"code":101,"indent":0,"parameters":["",0,0,2]},{"code":401,"indent":0,"parameters":["\\N<Naoto>(I knew it... you weren't satisfied...)"]},{"code":101,"indent":0,"parameters":["",0,0,2]},{"code":401,"indent":0,"parameters":["\\N<Naoto>(Your body is burning, is it not... Kaede?)"]},{"code":101,"indent":0,"parameters":["",0,0,2]},{"code":401,"indent":0,"parameters":["\\N<Kaede>Ngh... ahh..."]},{"code":401,"indent":0,"parameters":["Mhmm... I'm coming... ahhh...!"]},{"code":224,"indent":0,"parameters":[[255,255,255,255],60,true]},{"code":224,"indent":0,"parameters":[[255,255,255,255],60,true]},{"code":224,"indent":0,"parameters":[[255,255,255,255],60,true]},{"code":101,"indent":0,"parameters":["",0,0,2]},{"code":401,"indent":0,"parameters":["\\N<Kaede>Ngh!"]},{"code":101,"indent":0,"parameters":["",0,0,2]},{"code":401,"indent":0,"parameters":["\\N<Naoto>(Kaede...)"]},{"code":230,"indent":0,"parameters":[60]},{"code":242,"indent":0,"parameters":[3]},{"code":246,"indent":0,"parameters":[3]},{"code":221,"indent":0,"parameters":[]},{"code":235,"indent":0,"parameters":[1]},{"code":121,"indent":0,"parameters":[57,57,0]},{"code":223,"indent":0,"parameters":[[0,0,0,0],60,true]},{"code":121,"indent":0,"parameters":[1,56,1]},{"code":201,"indent":0,"parameters":[0,20,5,4,2,0]},{"code":0,"indent":0,"parameters":[]}],"moveFrequency":3,"moveRoute":{"list":[{"code":0,"parameters":[]}],"repeat":true,"skippable":false,"wait":false},"moveSpeed":3,"moveType":0,"priorityType":0,"stepAnime":true,"through":false,"trigger":1,"walkAnime":true},{"conditions":{"actorId":1,"actorValid":false,"itemId":1,"itemValid":false,"selfSwitchCh":"A","selfSwitchValid":false,"switch1Id":66,"switch1Valid":true,"switch2Id":1,"switch2Valid":false,"variableId":1,"variableValid":false,"variableValue":0},"directionFix":false,"image":{"tileId":0,"characterName":"!Flame","direction":2,"pattern":1,"characterIndex":6},"list":[{"code":205,"indent":0,"parameters":[-1,{"list":[{"code":19,"indent":null},{"code":0}],"repeat":false,"skippable":false,"wait":true}]},{"code":505,"indent":0,"parameters":[{"code":19,"indent":null}]},{"code":230,"indent":0,"parameters":[60]},{"code":213,"indent":0,"parameters":[-1,8,false]},{"code":230,"indent":0,"parameters":[60]},{"code":101,"indent":0,"parameters":["",0,0,2]},{"code":401,"indent":0,"parameters":["\\N<Naoto>Eh?... She's not here..."]},{"code":101,"indent":0,"parameters":["",0,0,2]},{"code":401,"indent":0,"parameters":["\\N<Naoto>Then... where did she go..."]},{"code":230,"indent":0,"parameters":[60]},{"code":221,"indent":0,"parameters":[]},{"code":121,"indent":0,"parameters":[67,67,0]},{"code":121,"indent":0,"parameters":[66,66,1]},{"code":222,"indent":0,"parameters":[]},{"code":0,"indent":0,"parameters":[]}],"moveFrequency":3,"moveRoute":{"list":[{"code":0,"parameters":[]}],"repeat":true,"skippable":false,"wait":false},"moveSpeed":3,"moveType":0,"priorityType":0,"stepAnime":true,"through":false,"trigger":1,"walkAnime":true},{"conditions":{"actorId":1,"actorValid":false,"itemId":1,"itemValid":false,"selfSwitchCh":"A","selfSwitchValid":false,"switch1Id":67,"switch1Valid":true,"switch2Id":1,"switch2Valid":false,"variableId":1,"variableValid":false,"variableValue":0},"directionFix":false,"image":{"characterIndex":0,"characterName":"","direction":2,"pattern":0,"tileId":0},"list":[{"code":0,"indent":0,"parameters":[]}],"moveFrequency":3,"moveRoute":{"list":[{"code":0,"parameters":[]}],"repeat":true,"skippable":false,"wait":false},"moveSpeed":3,"moveType":0,"priorityType":0,"stepAnime":false,"through":false,"trigger":0,"walkAnime":true}],"x":3,"y":4},{"id":3,"name":"楓1","note":"","pages":[{"conditions":{"actorId":1,"actorValid":false,"itemId":1,"itemValid":false,"selfSwitchCh":"A","selfSwitchValid":false,"switch1Id":56,"switch1Valid":true,"switch2Id":1,"switch2Valid":false,"variableId":1,"variableValid":false,"variableValue":0},"directionFix":false,"image":{"tileId":0,"characterName":"楓大人","direction":4,"pattern":1,"characterIndex":0},"list":[{"code":0,"indent":0,"parameters":[]}],"moveFrequency":3,"moveRoute":{"list":[{"code":0,"parameters":[]}],"repeat":true,"skippable":false,"wait":false},"moveSpeed":3,"moveType":0,"priorityType":1,"stepAnime":false,"through":false,"trigger":0,"walkAnime":true}],"x":3,"y":1},{"id":4,"name":"EV004","note":"","pages":[{"conditions":{"actorId":1,"actorValid":false,"itemId":1,"itemValid":false,"selfSwitchCh":"A","selfSwitchValid":false,"switch1Id":83,"switch1Valid":true,"switch2Id":1,"switch2Valid":false,"variableId":1,"variableValid":false,"variableValue":0},"directionFix":false,"image":{"tileId":0,"characterName":"","direction":2,"pattern":1,"characterIndex":6},"list":[{"code":230,"indent":0,"parameters":[60]},{"code":101,"indent":0,"parameters":["",0,0,2]},{"code":401,"indent":0,"parameters":["\\N<Naoto>K-Kaede..."]},{"code":101,"indent":0,"parameters":["",0,0,2]},{"code":401,"indent":0,"parameters":["\\N<Kaede>Naoto...?"]},{"code":101,"indent":0,"parameters":["",0,0,2]},{"code":401,"indent":0,"parameters":["\\N<Naoto>I-I'm next to go in..."]},{"code":101,"indent":0,"parameters":["",0,0,2]},{"code":401,"indent":0,"parameters":["\\N<Kaede>Ah, yes! Let me clean up first...!"]},{"code":401,"indent":0,"parameters":["Just give me a moment...!"]},{"code":221,"indent":0,"parameters":[]},{"code":121,"indent":0,"parameters":[84,84,0]},{"code":205,"indent":0,"parameters":[5,{"list":[{"code":39,"indent":null},{"code":37,"indent":null},{"code":1,"indent":null},{"code":0}],"repeat":false,"skippable":false,"wait":true}]},{"code":505,"indent":0,"parameters":[{"code":39,"indent":null}]},{"code":505,"indent":0,"parameters":[{"code":37,"indent":null}]},{"code":505,"indent":0,"parameters":[{"code":1,"indent":null}]},{"code":205,"indent":0,"parameters":[-1,{"list":[{"code":1,"indent":null},{"code":19,"indent":null},{"code":0}],"repeat":false,"skippable":false,"wait":true}]},{"code":505,"indent":0,"parameters":[{"code":1,"indent":null}]},{"code":505,"indent":0,"parameters":[{"code":19,"indent":null}]},{"code":222,"indent":0,"parameters":[]},{"code":230,"indent":0,"parameters":[60]},{"code":205,"indent":0,"parameters":[5,{"list":[{"code":40,"indent":null},{"code":44,"parameters":[{"name":"お風呂のドア","volume":90,"pitch":100,"pan":0}],"indent":null},{"code":0}],"repeat":false,"skippable":false,"wait":true}]},{"code":505,"indent":0,"parameters":[{"code":40,"indent":null}]},{"code":505,"indent":0,"parameters":[{"code":44,"parameters":[{"name":"お風呂のドア","volume":90,"pitch":100,"pan":0}],"indent":null}]},{"code":231,"indent":0,"parameters":[1,"kaede tatie d5",0,0,-180,0,53,53,255,0]},{"code":101,"indent":0,"parameters":["",0,0,2]},{"code":401,"indent":0,"parameters":["\\N<Kaede>Sorry for the wait."]},{"code":235,"indent":0,"parameters":[1]},{"code":101,"indent":0,"parameters":["",0,0,2]},{"code":401,"indent":0,"parameters":["\\N<Naoto>..."]},{"code":231,"indent":0,"parameters":[1,"kaede tatie d4",0,0,-180,0,53,53,255,0]},{"code":101,"indent":0,"parameters":["",0,0,2]},{"code":401,"indent":0,"parameters":["\\N<Kaede>What's wrong?"]},{"code":235,"indent":0,"parameters":[1]},{"code":101,"indent":0,"parameters":["",0,0,2]},{"code":401,"indent":0,"parameters":["\\N<Naoto>N-Nothing..."]},{"code":231,"indent":0,"parameters":[1,"kaede tatie d8",0,0,-180,0,53,53,255,0]},{"code":101,"indent":0,"parameters":["",0,0,2]},{"code":401,"indent":0,"parameters":["\\N<Kaede>...I see."]},{"code":235,"indent":0,"parameters":[1]},{"code":101,"indent":0,"parameters":["",0,0,2]},{"code":401,"indent":0,"parameters":["\\N<Naoto>Well then... I'm going into the bath..."]},{"code":231,"indent":0,"parameters":[1,"kaede tatie d8",0,0,-180,0,53,53,255,0]},{"code":101,"indent":0,"parameters":["",0,0,2]},{"code":401,"indent":0,"parameters":["\\N<Kaede>...Yeah."]},{"code":235,"indent":0,"parameters":[1]},{"code":205,"indent":0,"parameters":[5,{"list":[{"code":37,"indent":null},{"code":1,"indent":null},{"code":2,"indent":null},{"code":18,"indent":null},{"code":0}],"repeat":false,"skippable":false,"wait":true}]},{"code":505,"indent":0,"parameters":[{"code":37,"indent":null}]},{"code":505,"indent":0,"parameters":[{"code":1,"indent":null}]},{"code":505,"indent":0,"parameters":[{"code":2,"indent":null}]},{"code":505,"indent":0,"parameters":[{"code":18,"indent":null}]},{"code":205,"indent":0,"parameters":[-1,{"list":[{"code":37,"indent":null},{"code":4,"indent":null},{"code":15,"parameters":[60],"indent":null},{"code":39,"indent":null},{"code":44,"parameters":[{"name":"お風呂のドア","volume":90,"pitch":100,"pan":0}],"indent":null},{"code":0}],"repeat":false,"skippable":false,"wait":true}]},{"code":505,"indent":0,"parameters":[{"code":37,"indent":null}]},{"code":505,"indent":0,"parameters":[{"code":4,"indent":null}]},{"code":505,"indent":0,"parameters":[{"code":15,"parameters":[60],"indent":null}]},{"code":505,"indent":0,"parameters":[{"code":39,"indent":null}]},{"code":505,"indent":0,"parameters":[{"code":44,"parameters":[{"name":"お風呂のドア","volume":90,"pitch":100,"pan":0}],"indent":null}]},{"code":221,"indent":0,"parameters":[]},{"code":101,"indent":0,"parameters":["",0,0,2]},{"code":401,"indent":0,"parameters":["・・・・。"]},{"code":101,"indent":0,"parameters":["",0,0,2]},{"code":401,"indent":0,"parameters":["Unbeknownst to me..."]},{"code":101,"indent":0,"parameters":["",0,0,2]},{"code":401,"indent":0,"parameters":["Kaede was..."]},{"code":101,"indent":0,"parameters":["",0,0,2]},{"code":401,"indent":0,"parameters":["・・・・。"]},{"code":101,"indent":0,"parameters":["",0,0,2]},{"code":401,"indent":0,"parameters":["Venting her lust..."]},{"code":101,"indent":0,"parameters":["",0,0,2]},{"code":401,"indent":0,"parameters":["I knew it..."]},{"code":101,"indent":0,"parameters":["",0,0,2]},{"code":401,"indent":0,"parameters":["Was it... Shimoyama's fault?"]},{"code":101,"indent":0,"parameters":["",0,0,2]},{"code":401,"indent":0,"parameters":["*Pant, pant* Ngh... ahh..."]},{"code":101,"indent":0,"parameters":["",0,0,2]},{"code":401,"indent":0,"parameters":["Kaede..."]},{"code":101,"indent":0,"parameters":["",0,0,2]},{"code":401,"indent":0,"parameters":["・・・・。"]},{"code":101,"indent":0,"parameters":["",0,0,2]},{"code":401,"indent":0,"parameters":["Damnit... Shimoyama..."]},{"code":101,"indent":0,"parameters":["",0,0,2]},{"code":401,"indent":0,"parameters":["It's all his fault... thanks to him..."]},{"code":401,"indent":0,"parameters":["everything in my life has been messed up."]},{"code":101,"indent":0,"parameters":["",0,0,2]},{"code":401,"indent":0,"parameters":["・・・・。"]},{"code":101,"indent":0,"parameters":["",0,0,2]},{"code":401,"indent":0,"parameters":["No..."]},{"code":101,"indent":0,"parameters":["",0,0,2]},{"code":401,"indent":0,"parameters":["The one at fault... from the beginning... was me..."]},{"code":101,"indent":0,"parameters":["",0,0,2]},{"code":401,"indent":0,"parameters":["・・・・。"]},{"code":101,"indent":0,"parameters":["",0,0,2]},{"code":401,"indent":0,"parameters":["When I go back..."]},{"code":401,"indent":0,"parameters":["Kaede won't be there... anymore..."]},{"code":101,"indent":0,"parameters":["",0,0,2]},{"code":401,"indent":0,"parameters":["..."]},{"code":101,"indent":0,"parameters":["",0,0,2]},{"code":401,"indent":0,"parameters":["Shimoyama's house..."]},{"code":101,"indent":0,"parameters":["",0,0,2]},{"code":401,"indent":0,"parameters":["...Ngh."]},{"code":101,"indent":0,"parameters":["",0,0,2]},{"code":401,"indent":0,"parameters":["*Pant, pant* Ngh... ahh..."]},{"code":230,"indent":0,"parameters":[60]},{"code":101,"indent":0,"parameters":["",0,0,2]},{"code":401,"indent":0,"parameters":["..."]},{"code":101,"indent":0,"parameters":["",0,0,2]},{"code":401,"indent":0,"parameters":["..."]},{"code":101,"indent":0,"parameters":["",0,0,2]},{"code":401,"indent":0,"parameters":["......"]},{"code":230,"indent":0,"parameters":[60]},{"code":101,"indent":0,"parameters":["",0,0,2]},{"code":401,"indent":0,"parameters":["I guess it's time... to go back..."]},{"code":205,"indent":0,"parameters":[5,{"list":[{"code":39,"indent":null},{"code":0}],"repeat":false,"skippable":false,"wait":true}]},{"code":505,"indent":0,"parameters":[{"code":39,"indent":null}]},{"code":205,"indent":0,"parameters":[-1,{"list":[{"code":16,"indent":null},{"code":0}],"repeat":false,"skippable":false,"wait":true}]},{"code":505,"indent":0,"parameters":[{"code":16,"indent":null}]},{"code":222,"indent":0,"parameters":[]},{"code":230,"indent":0,"parameters":[60]},{"code":205,"indent":0,"parameters":[-1,{"list":[{"code":40,"indent":null},{"code":38,"indent":null},{"code":44,"parameters":[{"name":"お風呂のドア","volume":90,"pitch":100,"pan":0}],"indent":null},{"code":0}],"repeat":false,"skippable":false,"wait":true}]},{"code":505,"indent":0,"parameters":[{"code":40,"indent":null}]},{"code":505,"indent":0,"parameters":[{"code":38,"indent":null}]},{"code":505,"indent":0,"parameters":[{"code":44,"parameters":[{"name":"お風呂のドア","volume":90,"pitch":100,"pan":0}],"indent":null}]},{"code":230,"indent":0,"parameters":[60]},{"code":221,"indent":0,"parameters":[]},{"code":121,"indent":0,"parameters":[85,85,0]},{"code":121,"indent":0,"parameters":[1,84,1]},{"code":222,"indent":0,"parameters":[]},{"code":0,"indent":0,"parameters":[]}],"moveFrequency":3,"moveRoute":{"list":[{"code":0,"parameters":[]}],"repeat":true,"skippable":false,"wait":false},"moveSpeed":3,"moveType":0,"priorityType":0,"stepAnime":false,"through":false,"trigger":1,"walkAnime":true},{"conditions":{"actorId":1,"actorValid":false,"itemId":1,"itemValid":false,"selfSwitchCh":"A","selfSwitchValid":false,"switch1Id":85,"switch1Valid":true,"switch2Id":1,"switch2Valid":false,"variableId":1,"variableValid":false,"variableValue":0},"directionFix":false,"image":{"characterIndex":0,"characterName":"","direction":2,"pattern":0,"tileId":0},"list":[{"code":0,"indent":0,"parameters":[]}],"moveFrequency":3,"moveRoute":{"list":[{"code":0,"parameters":[]}],"repeat":true,"skippable":false,"wait":false},"moveSpeed":3,"moveType":0,"priorityType":0,"stepAnime":false,"through":false,"trigger":0,"walkAnime":true},{"conditions":{"actorId":1,"actorValid":false,"itemId":1,"itemValid":false,"selfSwitchCh":"A","selfSwitchValid":false,"switch1Id":135,"switch1Valid":true,"switch2Id":1,"switch2Valid":false,"variableId":1,"variableValid":false,"variableValue":0},"directionFix":false,"image":{"characterIndex":0,"characterName":"","direction":2,"pattern":0,"tileId":0},"list":[{"code":250,"indent":0,"parameters":[{"name":"シャワーの音","volume":90,"pitch":100,"pan":0}]},{"code":230,"indent":0,"parameters":[120]},{"code":213,"indent":0,"parameters":[-1,8,false]},{"code":230,"indent":0,"parameters":[60]},{"code":251,"indent":0,"parameters":[]},{"code":0,"indent":0,"parameters":[]}],"moveFrequency":3,"moveRoute":{"list":[{"code":0,"parameters":[]}],"repeat":true,"skippable":false,"wait":false},"moveSpeed":3,"moveType":0,"priorityType":0,"stepAnime":false,"through":false,"trigger":1,"walkAnime":true},{"conditions":{"actorId":1,"actorValid":false,"itemId":1,"itemValid":false,"selfSwitchCh":"A","selfSwitchValid":false,"switch1Id":136,"switch1Valid":true,"switch2Id":137,"switch2Valid":false,"variableId":1,"variableValid":false,"variableValue":0},"directionFix":false,"image":{"tileId":0,"characterName":"","direction":2,"pattern":1,"characterIndex":6},"list":[{"code":250,"indent":0,"parameters":[{"name":"シャワーの音","volume":5,"pitch":100,"pan":0}]},{"code":230,"indent":0,"parameters":[60]},{"code":213,"indent":0,"parameters":[-1,8,false]},{"code":230,"indent":0,"parameters":[60]},{"code":213,"indent":0,"parameters":[-1,1,false]},{"code":241,"indent":0,"parameters":[{"name":"kaede喘ぎ声(小) (1)","volume":90,"pitch":100,"pan":0}]},{"code":245,"indent":0,"parameters":[{"name":"クチュ音１（スロー）","volume":90,"pitch":100,"pan":0}]},{"code":231,"indent":0,"parameters":[1,"kage huroba onani1",0,0,0,0,100,100,0,0]},{"code":232,"indent":0,"parameters":[1,0,0,0,0,0,100,100,255,0,60,true]},{"code":101,"indent":0,"parameters":["",0,0,2]},{"code":401,"indent":0,"parameters":["\\N<Kaede>Ngh... ahn...!"]},{"code":101,"indent":0,"parameters":["",0,0,2]},{"code":401,"indent":0,"parameters":["\\N<Naoto>K-Kaede..."]},{"code":101,"indent":0,"parameters":["",0,0,2]},{"code":401,"indent":0,"parameters":["\\N<Kaede>Ahh... ngh... ahn...!"]},{"code":101,"indent":0,"parameters":["",0,0,2]},{"code":401,"indent":0,"parameters":["\\N<Kaede>N-Nooo... I'm feeling it too much..."]},{"code":101,"indent":0,"parameters":["",0,0,2]},{"code":401,"indent":0,"parameters":["\\N<Kaede>N-No more... ngh...!"]},{"code":101,"indent":0,"parameters":["",0,0,2]},{"code":401,"indent":0,"parameters":["\\N<Naoto>Wha-..."]},{"code":101,"indent":0,"parameters":["",0,0,2]},{"code":401,"indent":0,"parameters":["\\N<Kaede>Ahn... ngh... ahhh...!"]},{"code":101,"indent":0,"parameters":["",0,0,2]},{"code":401,"indent":0,"parameters":["\\N<Naoto>...What's going on..."]},{"code":101,"indent":0,"parameters":["",0,0,2]},{"code":401,"indent":0,"parameters":["\\N<Kaede>Ahh... ngh... ahhh..."]},{"code":101,"indent":0,"parameters":["",0,0,2]},{"code":401,"indent":0,"parameters":["\\N<Naoto>What's going on at the guesthouse..."]},{"code":101,"indent":0,"parameters":["",0,0,2]},{"code":401,"indent":0,"parameters":["\\N<Kaede>Ahh... I'm coming..."]},{"code":101,"indent":0,"parameters":["",0,0,2]},{"code":401,"indent":0,"parameters":["\\N<Naoto>... What happened... here...?"]},{"code":230,"indent":0,"parameters":[60]},{"code":221,"indent":0,"parameters":[]},{"code":242,"indent":0,"parameters":[3]},{"code":246,"indent":0,"parameters":[3]},{"code":101,"indent":0,"parameters":["",0,0,2]},{"code":401,"indent":0,"parameters":["\\N<Kaede>Aaahhhnnn...!!!"]},{"code":235,"indent":0,"parameters":[1]},{"code":101,"indent":0,"parameters":["",0,0,2]},{"code":401,"indent":0,"parameters":["..."]},{"code":101,"indent":0,"parameters":["",0,0,2]},{"code":401,"indent":0,"parameters":["..."]},{"code":101,"indent":0,"parameters":["",0,0,2]},{"code":401,"indent":0,"parameters":["......"]},{"code":223,"indent":0,"parameters":[[0,0,0,0],60,true]},{"code":121,"indent":0,"parameters":[138,138,0]},{"code":121,"indent":0,"parameters":[1,137,1]},{"code":201,"indent":0,"parameters":[0,20,5,4,2,0]},{"code":0,"indent":0,"parameters":[]}],"moveFrequency":3,"moveRoute":{"list":[{"code":0,"parameters":[]}],"repeat":true,"skippable":false,"wait":false},"moveSpeed":3,"moveType":0,"priorityType":0,"stepAnime":false,"through":false,"trigger":1,"walkAnime":true}],"x":6,"y":7},{"id":5,"name":"楓2","note":"","pages":[{"conditions":{"actorId":1,"actorValid":false,"itemId":1,"itemValid":false,"selfSwitchCh":"A","selfSwitchValid":false,"switch1Id":84,"switch1Valid":true,"switch2Id":1,"switch2Valid":false,"variableId":1,"variableValid":false,"variableValue":0},"directionFix":false,"image":{"tileId":0,"characterName":"楓大人","direction":2,"pattern":1,"characterIndex":0},"list":[{"code":0,"indent":0,"parameters":[]}],"moveFrequency":3,"moveRoute":{"list":[{"code":0,"parameters":[]}],"repeat":true,"skippable":false,"wait":false},"moveSpeed":3,"moveType":0,"priorityType":1,"stepAnime":false,"through":false,"trigger":0,"walkAnime":true}],"x":6,"y":6},{"id":6,"name":"EV006","note":"","pages":[{"conditions":{"actorId":1,"actorValid":false,"itemId":1,"itemValid":false,"selfSwitchCh":"A","selfSwitchValid":false,"switch1Id":211,"switch1Valid":true,"switch2Id":1,"switch2Valid":false,"variableId":1,"variableValid":false,"variableValue":0},"directionFix":false,"image":{"tileId":0,"characterName":"","direction":2,"pattern":1,"characterIndex":6},"list":[{"code":222,"indent":0,"parameters":[]},{"code":205,"indent":0,"parameters":[-1,{"list":[{"code":19,"indent":null},{"code":0}],"repeat":false,"skippable":false,"wait":true}]},{"code":505,"indent":0,"parameters":[{"code":19,"indent":null}]},{"code":230,"indent":0,"parameters":[60]},{"code":213,"indent":0,"parameters":[-1,1,false]},{"code":230,"indent":0,"parameters":[60]},{"code":101,"indent":0,"parameters":["",0,0,2]},{"code":401,"indent":0,"parameters":["\\N<Naoto>(Huh...?)"]},{"code":230,"indent":0,"parameters":[60]},{"code":241,"indent":0,"parameters":[{"name":"kaede吐息 (1)","volume":90,"pitch":100,"pan":0}]},{"code":245,"indent":0,"parameters":[{"name":"くちゅ音１","volume":90,"pitch":100,"pan":0}]},{"code":231,"indent":0,"parameters":[1,"kaede onani1　kage",0,0,0,0,100,100,0,0]},{"code":232,"indent":0,"parameters":[1,0,0,0,0,0,100,100,255,0,60,true]},{"code":101,"indent":0,"parameters":["",0,0,2]},{"code":401,"indent":0,"parameters":["\\N<Kaede>Ahn... mhmm... ngh..."]},{"code":101,"indent":0,"parameters":["",0,0,2]},{"code":401,"indent":0,"parameters":["\\N<Naoto>(K-Kaede...?)"]},{"code":101,"indent":0,"parameters":["",0,0,2]},{"code":401,"indent":0,"parameters":["\\N<Kaede>Ngh... mhmm... ahh..."]},{"code":101,"indent":0,"parameters":["",0,0,2]},{"code":401,"indent":0,"parameters":["\\N<Naoto>(I knew it... you weren't satisfied...)"]},{"code":101,"indent":0,"parameters":["",0,0,2]},{"code":401,"indent":0,"parameters":["\\N<Naoto>(Your body is burning, is it not... Kaede?)"]},{"code":101,"indent":0,"parameters":["",0,0,2]},{"code":401,"indent":0,"parameters":["\\N<Kaede>Ngh... ahh..."]},{"code":401,"indent":0,"parameters":["Mhmm... I'm coming... ahhh...!"]},{"code":224,"indent":0,"parameters":[[255,255,255,255],60,true]},{"code":224,"indent":0,"parameters":[[255,255,255,255],60,true]},{"code":224,"indent":0,"parameters":[[255,255,255,255],60,true]},{"code":101,"indent":0,"parameters":["",0,0,2]},{"code":401,"indent":0,"parameters":["\\N<Kaede>Ngh!"]},{"code":101,"indent":0,"parameters":["",0,0,2]},{"code":401,"indent":0,"parameters":["\\N<Naoto>(Kaede...)"]},{"code":230,"indent":0,"parameters":[60]},{"code":242,"indent":0,"parameters":[3]},{"code":246,"indent":0,"parameters":[3]},{"code":221,"indent":0,"parameters":[]},{"code":235,"indent":0,"parameters":[1]},{"code":121,"indent":0,"parameters":[1,1000,1]},{"code":223,"indent":0,"parameters":[[0,0,0,0],60,true]},{"code":201,"indent":0,"parameters":[0,22,7,5,4,0]},{"code":222,"indent":0,"parameters":[]},{"code":0,"indent":0,"parameters":[]}],"moveFrequency":3,"moveRoute":{"list":[{"code":0,"parameters":[]}],"repeat":true,"skippable":false,"wait":false},"moveSpeed":3,"moveType":0,"priorityType":0,"stepAnime":false,"through":false,"trigger":3,"walkAnime":true}],"x":4,"y":0},{"id":7,"name":"EV007","note":"","pages":[{"conditions":{"actorId":1,"actorValid":false,"itemId":1,"itemValid":false,"selfSwitchCh":"A","selfSwitchValid":false,"switch1Id":226,"switch1Valid":true,"switch2Id":137,"switch2Valid":false,"variableId":1,"variableValid":false,"variableValue":0},"directionFix":false,"image":{"tileId":0,"characterName":"","direction":2,"pattern":1,"characterIndex":6},"list":[{"code":222,"indent":0,"parameters":[]},{"code":250,"indent":0,"parameters":[{"name":"シャワーの音","volume":5,"pitch":100,"pan":0}]},{"code":230,"indent":0,"parameters":[60]},{"code":213,"indent":0,"parameters":[-1,8,false]},{"code":230,"indent":0,"parameters":[60]},{"code":213,"indent":0,"parameters":[-1,1,false]},{"code":241,"indent":0,"parameters":[{"name":"kaede喘ぎ声(小) (1)","volume":90,"pitch":100,"pan":0}]},{"code":245,"indent":0,"parameters":[{"name":"クチュ音１（スロー）","volume":90,"pitch":100,"pan":0}]},{"code":231,"indent":0,"parameters":[1,"kage huroba onani1",0,0,0,0,100,100,0,0]},{"code":232,"indent":0,"parameters":[1,0,0,0,0,0,100,100,255,0,60,true]},{"code":101,"indent":0,"parameters":["",0,0,2]},{"code":401,"indent":0,"parameters":["\\N<Kaede>Ngh... ahn...!"]},{"code":101,"indent":0,"parameters":["",0,0,2]},{"code":401,"indent":0,"parameters":["\\N<Naoto>K-Kaede..."]},{"code":101,"indent":0,"parameters":["",0,0,2]},{"code":401,"indent":0,"parameters":["\\N<Kaede>Ahh... ngh... ahn...!"]},{"code":101,"indent":0,"parameters":["",0,0,2]},{"code":401,"indent":0,"parameters":["\\N<Kaede>N-Nooo... I'm feeling it too much..."]},{"code":101,"indent":0,"parameters":["",0,0,2]},{"code":401,"indent":0,"parameters":["\\N<Kaede>N-No more... ngh...!"]},{"code":101,"indent":0,"parameters":["",0,0,2]},{"code":401,"indent":0,"parameters":["\\N<Naoto>Wha-..."]},{"code":101,"indent":0,"parameters":["",0,0,2]},{"code":401,"indent":0,"parameters":["\\N<Kaede>Ahn... ngh... ahhh...!"]},{"code":101,"indent":0,"parameters":["",0,0,2]},{"code":401,"indent":0,"parameters":["\\N<Naoto>...What's going on..."]},{"code":101,"indent":0,"parameters":["",0,0,2]},{"code":401,"indent":0,"parameters":["\\N<Kaede>Ahh... ngh... ahhh..."]},{"code":101,"indent":0,"parameters":["",0,0,2]},{"code":401,"indent":0,"parameters":["\\N<Naoto>What's going on at the guesthouse..."]},{"code":101,"indent":0,"parameters":["",0,0,2]},{"code":401,"indent":0,"parameters":["\\N<Kaede>Ahh... I'm coming..."]},{"code":101,"indent":0,"parameters":["",0,0,2]},{"code":401,"indent":0,"parameters":["\\N<Naoto>... What happened... here...?"]},{"code":230,"indent":0,"parameters":[60]},{"code":221,"indent":0,"parameters":[]},{"code":242,"indent":0,"parameters":[3]},{"code":246,"indent":0,"parameters":[3]},{"code":101,"indent":0,"parameters":["",0,0,2]},{"code":401,"indent":0,"parameters":["\\N<Kaede>Aaahhhnnn...!!!"]},{"code":235,"indent":0,"parameters":[1]},{"code":223,"indent":0,"parameters":[[0,0,0,0],60,true]},{"code":121,"indent":0,"parameters":[1,1000,1]},{"code":201,"indent":0,"parameters":[0,22,13,9,4,0]},{"code":222,"indent":0,"parameters":[]},{"code":0,"indent":0,"parameters":[]}],"moveFrequency":3,"moveRoute":{"list":[{"code":0,"parameters":[]}],"repeat":true,"skippable":false,"wait":false},"moveSpeed":3,"moveType":0,"priorityType":0,"stepAnime":false,"through":false,"trigger":3,"walkAnime":true}],"x":8,"y":4}]}